__init__.py
base_client.py
client_abstract_methods.py
metric.py
joint_ml-0.1.0.dist-info/METADATA
joint_ml-0.1.0.dist-info/WHEEL
joint_ml-0.1.0.dist-info/RECORD
