Metadata-Version: 2.1
Name: joint-ml
Version: 0.1.0
Summary: 
Author: s.nikishonkov
Author-email: s.nikishonkov@astondevs.ru
Requires-Python: >=3.10,<4.0
Classifier: Programming Language :: Python :: 3
Classifier: Programming Language :: Python :: 3.10
Classifier: Programming Language :: Python :: 3.11
Requires-Dist: pandas (>=2.1.0,<3.0.0)
Requires-Dist: torch (>=2.0.1,<3.0.0)
